airbase/__init__.py
airbase/airtable.py
airbase/decorators.py
airbase/exceptions.py
airbase/py.typed
airbase/tools.py
airbase/urls.py
airbase/validations.py
airbase/utils/__init__.py
airbase/utils/logger.py
airbase/utils/semaphore.py
airtable_async-0.0.1b12.dist-info/LICENSE
airtable_async-0.0.1b12.dist-info/METADATA
airtable_async-0.0.1b12.dist-info/WHEEL
airtable_async-0.0.1b12.dist-info/top_level.txt
airtable_async-0.0.1b12.dist-info/RECORD
