Metadata-Version: 2.1
Name: airtable-async
Version: 0.0.1b12
Summary: An asynchronous Python API Wrapper for the Airtable API
Home-page: https://github.com/lfparis/airbase
Author: Luis Felipe Paris
Author-email: lfparis@gmail.com
License: The MIT License (MIT)
Keywords: airtable,api,async,async.io
Classifier: Development Status :: 2 - Pre-Alpha
Classifier: Environment :: Console
Classifier: Framework :: AsyncIO
Classifier: Intended Audience :: Developers
Classifier: Programming Language :: Python
Classifier: Topic :: Software Development
Classifier: Programming Language :: Python :: 3.7
Classifier: Programming Language :: Python :: 3.8
Classifier: Programming Language :: Python :: 3.9
Classifier: Programming Language :: Python :: Implementation :: CPython
Requires-Python: >=3.7
License-File: LICENSE
Requires-Dist: aiohttp
Provides-Extra: tools
Requires-Dist: pandas ; extra == 'tools'
